morphopretext/Dictionaries_En.py
morphopretext/Dictionaries_Fa.py
morphopretext/__init__.py
morphopretext/english_text_preprocessor.py
morphopretext/persian_text_preprocessor.py
morphopretext-0.2.0.dist-info/licenses/LICENSE
morphopretext-0.2.0.dist-info/METADATA
morphopretext-0.2.0.dist-info/WHEEL
morphopretext-0.2.0.dist-info/top_level.txt
morphopretext-0.2.0.dist-info/RECORD
