Metadata-Version: 2.4
Name: MorphoPreText
Version: 0.2.0
Summary: A bilingual text preprocessing toolkit for English and Persian.
Home-page: https://github.com/ghaskari/MorphoPreText
Author: Ghazal Askari
Author-email: g.askari1037@gmail.com
Keywords: text preprocessing NLP English Persian bilingual
Classifier: Programming Language :: Python :: 3
Classifier: License :: OSI Approved :: MIT License
Classifier: Operating System :: OS Independent
Requires-Python: >=3.8
License-File: LICENSE
Requires-Dist: emoji==2.14.0
Requires-Dist: nltk==3.2.2
Requires-Dist: pandas==2.2.3
Requires-Dist: scikit-learn==1.6.0
Requires-Dist: pyspellchecker==0.8.2
Requires-Dist: parsivar==0.2.2
Requires-Dist: spacy==3.8.3
Requires-Dist: openpyxl==3.1.5
Requires-Dist: jdatetime==5.0.0
Dynamic: author
Dynamic: author-email
Dynamic: classifier
Dynamic: description
Dynamic: description-content-type
Dynamic: home-page
Dynamic: keywords
Dynamic: license-file
Dynamic: requires-dist
Dynamic: requires-python
Dynamic: summary
